[
  {
    "package": "linelist",
    "url": "https://github.com/epiverse-trace/linelist"
  },
  {
    "package": "finalsize",
    "url": "https://github.com/epiverse-trace/finalsize"
  },
  {
    "package": "bpmodels",
    "url": "https://github.com/epiverse-trace/bpmodels"
  },
  {
    "package": "cfr",
    "url": "https://github.com/epiverse-trace/cfr"
  },
  {
    "package": "serofoi",
    "url": "https://github.com/epiverse-trace/serofoi",
    "branch": "fix-r-universe"
  },
  {
    "package": "superspreading",
    "url": "https://github.com/epiverse-trace/superspreading"
  }
]
